DeeperLearning/NNClasses.py
DeeperLearning/__init__.py
deeperlearning-0.0.2.dist-info/LICENSE.txt
deeperlearning-0.0.2.dist-info/METADATA
deeperlearning-0.0.2.dist-info/WHEEL
deeperlearning-0.0.2.dist-info/top_level.txt
deeperlearning-0.0.2.dist-info/RECORD
