Metadata-Version: 2.1
Name: deeperlearning
Version: 0.0.2
Summary: A package with tools for Neural networks
Home-page: https://github.com/riioze/deeperlearning
Author: riioze
Author-email: riioze0@gmail.com
License: UNKNOWN
Platform: UNKNOWN
Classifier: Programming Language :: Python :: 3
Classifier: License :: OSI Approved :: MIT License
Classifier: Operating System :: OS Independent
Requires-Python: >=3.6
License-File: LICENSE.txt
Requires-Dist: numpy
